aigpy/LockHelper.py
aigpy/__init__.py
aigpy/cmdHelper.py
aigpy/convertHelper.py
aigpy/dictHelper.py
aigpy/downloadHelper.py
aigpy/fileHelper.py
aigpy/m3u8Helper.py
aigpy/modelHelper.py
aigpy/netHelper.py
aigpy/pathHelper.py
aigpy/pipHelper.py
aigpy/progressHelper.py
aigpy/stringHelper.py
aigpy/systemHelper.py
aigpy/tagHelper.py
aigpy/threadHelper.py
aigpy_test-2021.2.18.1.dist-info/LICENSE
aigpy_test-2021.2.18.1.dist-info/METADATA
aigpy_test-2021.2.18.1.dist-info/WHEEL
aigpy_test-2021.2.18.1.dist-info/top_level.txt
aigpy_test-2021.2.18.1.dist-info/RECORD
