Metadata-Version: 2.1
Name: aigpy-test
Version: 2021.2.18.1
Summary: Python Common Tool
Home-page: UNKNOWN
Author: Yaronzz
Author-email: yaronhuang@foxmail.com
License: MIT Licence
Platform: any
Requires-Dist: requests
Requires-Dist: colorama
Requires-Dist: mutagen
